fbjson2table/__init__.py
fbjson2table/func_lib.py
fbjson2table/specifc_outputs.py
fbjson2table/specific_outputs.py
fbjson2table/table_class.py
fbjson2table-1.2.0.dist-info/LICENSE.txt
fbjson2table-1.2.0.dist-info/METADATA
fbjson2table-1.2.0.dist-info/WHEEL
fbjson2table-1.2.0.dist-info/top_level.txt
fbjson2table-1.2.0.dist-info/RECORD
