Metadata-Version: 2.1
Name: fbjson2table
Version: 1.2.0
Summary: Parse Facebook archive JSON files to tables
Home-page: https://github.com/numbersprotocol/fb-json2table
Author: Numbers
Author-email: hi@numbersprotocol.io
License: UNKNOWN
Platform: UNKNOWN
Classifier: Programming Language :: Python :: 3
Classifier: License :: OSI Approved :: GNU General Public License v3 (GPLv3)
Classifier: Operating System :: OS Independent
Requires-Python: >=3.5
Requires-Dist: pandas (>=0.24.1)
